kalabash_pdfcredentials/__init__.py
kalabash_pdfcredentials/apps.py
kalabash_pdfcredentials/constants.py
kalabash_pdfcredentials/documents.py
kalabash_pdfcredentials/forms.py
kalabash_pdfcredentials/handlers.py
kalabash_pdfcredentials/kalmonak_extension.py
kalabash_pdfcredentials/lib.py
kalabash_pdfcredentials/models.py
kalabash_pdfcredentials/rfc6266.py
kalabash_pdfcredentials/tests.py
kalabash_pdfcredentials/urls.py
kalabash_pdfcredentials/views.py
kalabash_pdfcredentials/locale/en/LC_MESSAGES/django.mo
kalabash_pdfcredentials/locale/en/LC_MESSAGES/django.po
kalabash_pdfcredentials/locale/fr/LC_MESSAGES/django.mo
kalabash_pdfcredentials/locale/fr/LC_MESSAGES/django.po
kalabash_pdfcredentials-1.4.9.dist-info/LICENSE
kalabash_pdfcredentials-1.4.9.dist-info/METADATA
kalabash_pdfcredentials-1.4.9.dist-info/WHEEL
kalabash_pdfcredentials-1.4.9.dist-info/top_level.txt
kalabash_pdfcredentials-1.4.9.dist-info/RECORD
